[{"iob":0.202,"activity":0.0001,"bolussnooze":0,"basaliob":0.202,"netbasalinsulin":0.1,"hightempinsulin":0.4,"time":"2016-05-28T11:54:10.000Z"},{"iob":0.15,"activity":0.0004,"bolussnooze":0,"basaliob":0.15,"netbasalinsulin":0.05,"hightempinsulin":0.4,"time":"2016-05-28T11:59:10.000Z"},{"iob":0.096,"activity":0.0007,"bolussnooze":0,"basaliob":0.096,"netbasalinsulin":0,"hightempinsulin":0.4,"time":"2016-05-28T12:04:10.000Z"},{"iob":0.091,"activity":0.001,"bolussnooze":0,"basaliob":0.091,"netbasalinsulin":0,"hightempinsulin":0.4,"time":"2016-05-28T12:09:10.000Z"},{"iob":0.034,"activity":0.0013,"bolussnooze":0,"basaliob":0.034,"netbasalinsulin":0,"hightempinsulin":0.4,"time":"2016-05-28T12:14:10.000Z"},{"iob":0.026,"activity":0.0016,"bolussnooze":0,"basaliob":0.026,"netbasalinsulin":0,"hightempinsulin":0.4,"time":"2016-05-28T12:19:10.000Z"},{"iob":0.018,"activity":0.0017,"bolussnooze":0,"basaliob":0.018,"netbasalinsulin":0,"hightempinsulin":0.4,"time":"2016-05-28T12:24:10.000Z"},{"iob":0.009,"activity":0.0018,"bolussnooze":0,"basaliob":0.009,"netbasalinsulin":0,"hightempinsulin":0.4,"time":"2016-05-28T12:29:10.000Z"},{"iob":0,"activity":0.0018,"bolussnooze":0,"basaliob":0,"netbasalinsulin":0,"hightempinsulin":0.4,"time":"2016-05-28T12:34:10.000Z"},{"iob":-0.008,"activity":0.0017,"bolussnooze":0,"basaliob":-0.008,"netbasalinsulin":0,"hightempinsulin":0.4,"time":"2016-05-28T12:39:10.000Z"},{"iob":-0.016,"activity":0.0015,"bolussnooze":0,"basaliob":-0.016,"netbasalinsulin":0,"hightempinsulin":0.4,"time":"2016-05-28T12:44:10.000Z"},{"iob":-0.022,"activity":0.0013,"bolussnooze":0,"basaliob":-0.022,"netbasalinsulin":0,"hightempinsulin":0.4,"time":"2016-05-28T12:49:10.000Z"},{"iob":-0.027,"activity":0.001,"bolussnooze":0,"basaliob":-0.027,"netbasalinsulin":0,"hightempinsulin":0.4,"time":"2016-05-28T12:54:10.000Z"},{"iob":-0.031,"activity":0.0007,"bolussnooze":0,"basaliob":-0.031,"netbasalinsulin":0,"hightempinsulin":0.4,"time":"2016-05-28T12:59:10.000Z"},{"iob":-0.034,"activity":0.0005,"bolussnooze":0,"basaliob":-0.034,"netbasalinsulin":0,"hightempinsulin":0.4,"time":"2016-05-28T13:04:10.000Z"},{"iob":-0.035,"activity":0.0003,"bolussnooze":0,"basaliob":-0.035,"netbasalinsulin":0,"hightempinsulin":0.4,"time":"2016-05-28T13:09:10.000Z"},{"iob":-0.036,"activity":0.0002,"bolussnooze":0,"basaliob":-0.036,"netbasalinsulin":0,"hightempinsulin":0.4,"time":"2016-05-28T13:14:10.000Z"},{"iob":-0.037,"activity":0.0001,"bolussnooze":0,"basaliob":-0.037,"netbasalinsulin":0,"hightempinsulin":0.4,"time":"2016-05-28T13:19:10.000Z"},{"iob":-0.037,"activity":0,"bolussnooze":0,"basaliob":-0.037,"netbasalinsulin":0.05,"hightempinsulin":0.4,"time":"2016-05-28T13:24:10.000Z"},{"iob":-0.037,"activity":0,"bolussnooze":0,"basaliob":-0.037,"netbasalinsulin":0.1,"hightempinsulin":0.4,"time":"2016-05-28T13:29:10.000Z"},{"iob":-0.037,"activity":-0.0001,"bolussnooze":0,"basaliob":-0.037,"netbasalinsulin":0.1,"hightempinsulin":0.4,"time":"2016-05-28T13:34:10.000Z"},{"iob":-0.036,"activity":-0.0001,"bolussnooze":0,"basaliob":-0.036,"netbasalinsulin":0.15,"hightempinsulin":0.4,"time":"2016-05-28T13:39:10.000Z"},{"iob":-0.035,"activity":-0.0002,"bolussnooze":0,"basaliob":-0.035,"netbasalinsulin":0.2,"hightempinsulin":0.4,"time":"2016-05-28T13:44:10.000Z"},{"iob":-0.033,"activity":-0.0003,"bolussnooze":0,"basaliob":-0.033,"netbasalinsulin":0.2,"hightempinsulin":0.4,"time":"2016-05-28T13:49:10.000Z"},{"iob":-0.031,"activity":-0.0004,"bolussnooze":0,"basaliob":-0.031,"netbasalinsulin":0.2,"hightempinsulin":0.4,"time":"2016-05-28T13:54:10.000Z"},{"iob":-0.029,"activity":-0.0005,"bolussnooze":0,"basaliob":-0.029,"netbasalinsulin":0.2,"hightempinsulin":0.4,"time":"2016-05-28T13:59:10.000Z"},{"iob":-0.025,"activity":-0.0006,"bolussnooze":0,"basaliob":-0.025,"netbasalinsulin":0.15,"hightempinsulin":0.35,"time":"2016-05-28T14:04:10.000Z"},{"iob":-0.022,"activity":-0.0007,"bolussnooze":0,"basaliob":-0.022,"netbasalinsulin":0.1,"hightempinsulin":0.3,"time":"2016-05-28T14:09:10.000Z"},{"iob":-0.018,"activity":-0.0007,"bolussnooze":0,"basaliob":-0.018,"netbasalinsulin":0,"hightempinsulin":0.2,"time":"2016-05-28T14:14:10.000Z"},{"iob":-0.015,"activity":-0.0007,"bolussnooze":0,"basaliob":-0.015,"netbasalinsulin":-0.05,"hightempinsulin":0.15,"time":"2016-05-28T14:19:10.000Z"},{"iob":-0.011,"activity":-0.0007,"bolussnooze":0,"basaliob":-0.011,"netbasalinsulin":-0.1,"hightempinsulin":0.1,"time":"2016-05-28T14:24:10.000Z"},{"iob":-0.008,"activity":-0.0006,"bolussnooze":0,"basaliob":-0.008,"netbasalinsulin":-0.15,"hightempinsulin":0.05,"time":"2016-05-28T14:29:10.000Z"},{"iob":-0.006,"activity":-0.0005,"bolussnooze":0,"basaliob":-0.006,"netbasalinsulin":-0.2,"hightempinsulin":0,"time":"2016-05-28T14:34:10.000Z"},{"iob":-0.004,"activity":-0.0004,"bolussnooze":0,"basaliob":-0.004,"netbasalinsulin":-0.2,"hightempinsulin":0,"time":"2016-05-28T14:39:10.000Z"},{"iob":-0.002,"activity":-0.0003,"bolussnooze":0,"basaliob":-0.002,"netbasalinsulin":-0.2,"hightempinsulin":0,"time":"2016-05-28T14:44:10.000Z"},{"iob":-0.001,"activity":-0.0002,"bolussnooze":0,"basaliob":-0.001,"netbasalinsulin":-0.15,"hightempinsulin":0,"time":"2016-05-28T14:49:10.000Z"}]
