{
  "bg": 84, 
  "temp": "absolute", 
  "snoozeBG": 145, 
  "recieved": true, 
  "predBGs": {
    "COB": [
      84, 
      89, 
      94, 
      100, 
      105, 
      110, 
      115, 
      120, 
      125, 
      130, 
      135, 
      140, 
      144, 
      149, 
      153, 
      157, 
      161, 
      165, 
      168, 
      171, 
      173, 
      176, 
      178, 
      179, 
      181, 
      182, 
      183, 
      184, 
      184, 
      185
    ], 
    "aCOB": [
      84, 
      94, 
      104, 
      113, 
      121, 
      129, 
      136, 
      142, 
      148, 
      153, 
      158, 
      162, 
      165, 
      167, 
      169, 
      171, 
      173, 
      174, 
      176, 
      177, 
      178, 
      179, 
      179, 
      180, 
      181, 
      181, 
      181, 
      182
    ], 
    "IOB": [
      84, 
      89, 
      94, 
      98, 
      103, 
      107, 
      110, 
      114, 
      117, 
      120, 
      123, 
      125, 
      127, 
      129, 
      131, 
      133, 
      134, 
      136, 
      137, 
      138, 
      139, 
      140, 
      141, 
      142, 
      142, 
      142, 
      143, 
      143, 
      143, 
      143, 
      144
    ]
  }, 
  "rate": 1.625, 
  "reason": "COB: 15, Dev: 27, BGI: 0.84, ISF: 72.7, Target: 115; Eventual BG 185>=115, temp 0.85<1.655U/hr", 
  "eventualBG": 185, 
  "timestamp": "2016-05-20T23:07:11.697765", 
  "duration": 30, 
  "tick": "+6"
}