[
  {
    "direction": "Flat", 
    "noise": 1, 
    "sysTime": "2016-03-20T20:01:48.740-0700", 
    "xDrip_calculated_value": 113, 
    "xDrip_raw": 135, 
    "dateString": "2016-03-20T20:01:48.740-0700", 
    "sgv": 113, 
    "date": 1458529308740, 
    "xDrip_filtered": 134, 
    "xDrip_age_adjusted_raw_value": 135, 
    "unfiltered": 135000, 
    "rssi": 100, 
    "device": "xDrip-DexcomShare", 
    "filtered": 134000, 
    "xDrip_calculated_current_slope": 3.3414865605410534e-06, 
    "_id": "56ef646265110bbfc1927fde", 
    "type": "sgv"
  }, 
  {
    "direction": "Flat", 
    "noise": 1, 
    "sysTime": "2016-03-20T19:56:49.472-0700", 
    "xDrip_calculated_value": 112, 
    "xDrip_raw": 134, 
    "dateString": "2016-03-20T19:56:49.472-0700", 
    "sgv": 112, 
    "date": 1458529009472, 
    "xDrip_filtered": 135, 
    "xDrip_age_adjusted_raw_value": 134, 
    "unfiltered": 134000, 
    "rssi": 100, 
    "device": "xDrip-DexcomShare", 
    "filtered": 135000, 
    "xDrip_calculated_current_slope": 0, 
    "_id": "56ef633265110bbfc1927fdd", 
    "type": "sgv"
  }, 
  {
    "direction": "Flat", 
    "noise": 1, 
    "sysTime": "2016-03-20T19:51:49.472-0700", 
    "xDrip_calculated_value": 112, 
    "xDrip_raw": 134, 
    "dateString": "2016-03-20T19:51:49.472-0700", 
    "sgv": 112, 
    "date": 1458528709472, 
    "xDrip_filtered": 136, 
    "xDrip_age_adjusted_raw_value": 134, 
    "unfiltered": 134000, 
    "rssi": 100, 
    "device": "xDrip-DexcomShare", 
    "filtered": 136000, 
    "xDrip_calculated_current_slope": 0, 
    "_id": "56ef633265110bbfc1927fdc", 
    "type": "sgv"
  }, 
  {
    "direction": "Flat", 
    "noise": 1, 
    "sysTime": "2016-03-20T19:46:48.723-0700", 
    "xDrip_calculated_value": 112, 
    "xDrip_raw": 134, 
    "dateString": "2016-03-20T19:46:48.723-0700", 
    "sgv": 112, 
    "date": 1458528408723, 
    "xDrip_filtered": 136, 
    "xDrip_age_adjusted_raw_value": 134, 
    "unfiltered": 134000, 
    "rssi": 100, 
    "device": "xDrip-DexcomShare", 
    "filtered": 136000, 
    "xDrip_calculated_current_slope": -1.00182331843956e-05, 
    "_id": "56ef60fc65110bbfc1927fdb", 
    "type": "sgv"
  }, 
  {
    "direction": "Flat", 
    "noise": 1, 
    "sysTime": "2016-03-20T19:41:49.269-0700", 
    "xDrip_calculated_value": 115, 
    "xDrip_raw": 137, 
    "dateString": "2016-03-20T19:41:49.269-0700", 
    "sgv": 115, 
    "date": 1458528109269, 
    "xDrip_filtered": 136, 
    "xDrip_age_adjusted_raw_value": 137, 
    "unfiltered": 137000, 
    "rssi": 100, 
    "device": "xDrip-DexcomShare", 
    "filtered": 136000, 
    "xDrip_calculated_current_slope": 0, 
    "_id": "56ef5f8c65110bbfc1927fd9", 
    "type": "sgv"
  }, 
  {
    "direction": "Flat", 
    "noise": 1, 
    "sysTime": "2016-03-20T19:36:48.659-0700", 
    "xDrip_calculated_value": 115, 
    "xDrip_raw": 137, 
    "dateString": "2016-03-20T19:36:48.659-0700", 
    "sgv": 115, 
    "date": 1458527808659, 
    "xDrip_filtered": 135, 
    "xDrip_age_adjusted_raw_value": 137, 
    "unfiltered": 137000, 
    "rssi": 100, 
    "device": "xDrip-DexcomShare", 
    "filtered": 135000, 
    "xDrip_calculated_current_slope": 0, 
    "_id": "56ef5e6265110bbfc1927fd8", 
    "type": "sgv"
  }, 
  {
    "direction": "Flat", 
    "noise": 1, 
    "sysTime": "2016-03-20T19:31:49.927-0700", 
    "xDrip_calculated_value": 115, 
    "xDrip_raw": 137, 
    "dateString": "2016-03-20T19:31:49.927-0700", 
    "sgv": 115, 
    "date": 1458527509927, 
    "xDrip_filtered": 136, 
    "xDrip_age_adjusted_raw_value": 137, 
    "unfiltered": 137000, 
    "rssi": 100, 
    "device": "xDrip-DexcomShare", 
    "filtered": 136000, 
    "xDrip_calculated_current_slope": 6.654245408570668e-06, 
    "_id": "56ef5d7565110bbfc1927fd4", 
    "type": "sgv"
  }, 
  {
    "direction": "Flat", 
    "noise": 1, 
    "sysTime": "2016-03-20T19:26:49.367-0700", 
    "xDrip_calculated_value": 113, 
    "xDrip_raw": 135, 
    "dateString": "2016-03-20T19:26:49.367-0700", 
    "sgv": 113, 
    "date": 1458527209367, 
    "xDrip_filtered": 136, 
    "xDrip_age_adjusted_raw_value": 135, 
    "unfiltered": 135000, 
    "rssi": 100, 
    "device": "xDrip-DexcomShare", 
    "filtered": 136000, 
    "xDrip_calculated_current_slope": 0, 
    "_id": "56ef5c0965110bbfc1927fd3", 
    "type": "sgv"
  }, 
  {
    "direction": "Flat", 
    "noise": 1, 
    "sysTime": "2016-03-20T19:21:48.748-0700", 
    "xDrip_calculated_value": 113, 
    "xDrip_raw": 134, 
    "dateString": "2016-03-20T19:21:48.748-0700", 
    "sgv": 113, 
    "date": 1458526908748, 
    "xDrip_filtered": 136, 
    "xDrip_age_adjusted_raw_value": 134, 
    "unfiltered": 134000, 
    "rssi": 100, 
    "device": "xDrip-DexcomShare", 
    "filtered": 136000, 
    "xDrip_calculated_current_slope": -3.3354012821282527e-06, 
    "_id": "56ef5adc65110bbfc1927fcf", 
    "type": "sgv"
  }, 
  {
    "direction": "Flat", 
    "noise": 1, 
    "sysTime": "2016-03-20T19:16:48.934-0700", 
    "xDrip_calculated_value": 114, 
    "xDrip_raw": 135, 
    "dateString": "2016-03-20T19:16:48.934-0700", 
    "sgv": 114, 
    "date": 1458526608934, 
    "xDrip_filtered": 132, 
    "xDrip_age_adjusted_raw_value": 135, 
    "unfiltered": 135000, 
    "rssi": 100, 
    "device": "xDrip-DexcomShare", 
    "filtered": 132000, 
    "xDrip_calculated_current_slope": 0, 
    "_id": "56ef59ce65110bbfc1927fcd", 
    "type": "sgv"
  }
]