[
  {
    "filtered": 172000, 
    "direction": "FortyFiveUp", 
    "noise": 1, 
    "raw": 182, 
    "type": "sgv", 
    "_id": "571855bc65110bbfc192c948", 
    "sysTime": "2016-04-20T21:22:47.682-0700", 
    "dateString": "2016-04-20T21:22:47.682-0700", 
    "sgv": 176, 
    "device": "xDrip-DexcomShare", 
    "xDrip_filtered": 172, 
    "unfiltered": 177000, 
    "xDrip_raw": 177, 
    "date": 1461212567682, 
    "rssi": 100, 
    "xDrip_calculated_current_slope": 2.3338701234617295e-05, 
    "xDrip_age_adjusted_raw_value": 177, 
    "xDrip_calculated_value": 176
  }, 
  {
    "filtered": 163000, 
    "direction": "FortyFiveUp", 
    "noise": 1, 
    "raw": 181, 
    "type": "sgv", 
    "_id": "5718548d65110bbfc192c947", 
    "sysTime": "2016-04-20T21:17:47.751-0700", 
    "dateString": "2016-04-20T21:17:47.751-0700", 
    "sgv": 169, 
    "device": "xDrip-DexcomShare", 
    "xDrip_filtered": 163, 
    "unfiltered": 172000, 
    "xDrip_raw": 172, 
    "date": 1461212267751, 
    "rssi": 100, 
    "xDrip_calculated_current_slope": 2.000413418773213e-05, 
    "xDrip_age_adjusted_raw_value": 172, 
    "xDrip_calculated_value": 169
  }, 
  {
    "filtered": 152000, 
    "direction": "SingleUp", 
    "noise": 1, 
    "raw": 183, 
    "type": "sgv", 
    "_id": "5718538865110bbfc192c944", 
    "sysTime": "2016-04-20T21:12:47.813-0700", 
    "dateString": "2016-04-20T21:12:47.813-0700", 
    "sgv": 163, 
    "device": "xDrip-DexcomShare", 
    "xDrip_filtered": 152, 
    "unfiltered": 167000, 
    "xDrip_raw": 167, 
    "date": 1461211967813, 
    "rssi": 100, 
    "xDrip_calculated_current_slope": 1.6665444534067502e-05, 
    "xDrip_age_adjusted_raw_value": 167, 
    "xDrip_calculated_value": 163
  }, 
  {
    "filtered": 141000, 
    "direction": "SingleUp", 
    "noise": 1, 
    "raw": 190, 
    "type": "sgv", 
    "_id": "5718523865110bbfc192c943", 
    "sysTime": "2016-04-20T21:07:47.791-0700", 
    "dateString": "2016-04-20T21:07:47.791-0700", 
    "sgv": 158, 
    "device": "xDrip-DexcomShare", 
    "xDrip_filtered": 141, 
    "unfiltered": 163000, 
    "xDrip_raw": 163, 
    "date": 1461211667791, 
    "rssi": 100, 
    "xDrip_calculated_current_slope": 6.655861984045898e-05, 
    "xDrip_age_adjusted_raw_value": 163, 
    "xDrip_calculated_value": 158
  }, 
  {
    "filtered": 134000, 
    "direction": "FortyFiveUp", 
    "noise": 1, 
    "raw": 156, 
    "type": "sgv", 
    "_id": "5718510d65110bbfc192c942", 
    "sysTime": "2016-04-20T21:02:47.304-0700", 
    "dateString": "2016-04-20T21:02:47.304-0700", 
    "sgv": 138, 
    "device": "xDrip-DexcomShare", 
    "xDrip_filtered": 134, 
    "unfiltered": 147000, 
    "xDrip_raw": 147, 
    "date": 1461211367304, 
    "rssi": 100, 
    "xDrip_calculated_current_slope": 4.674832039963135e-05, 
    "xDrip_age_adjusted_raw_value": 147, 
    "xDrip_calculated_value": 138
  }, 
  {
    "filtered": 130000, 
    "direction": "Flat", 
    "noise": 1, 
    "raw": 132, 
    "type": "sgv", 
    "_id": "5718500065110bbfc192c93f", 
    "sysTime": "2016-04-20T20:57:47.828-0700", 
    "dateString": "2016-04-20T20:57:47.828-0700", 
    "sgv": 124, 
    "device": "xDrip-DexcomShare", 
    "xDrip_filtered": 130, 
    "unfiltered": 136000, 
    "xDrip_raw": 136, 
    "date": 1461211067828, 
    "rssi": 100, 
    "xDrip_calculated_current_slope": 2.333481120470963e-05, 
    "xDrip_age_adjusted_raw_value": 136, 
    "xDrip_calculated_value": 124
  }, 
  {
    "filtered": 129000, 
    "direction": "Flat", 
    "noise": 1, 
    "raw": 119, 
    "type": "sgv", 
    "_id": "57184eb165110bbfc192c93d", 
    "sysTime": "2016-04-20T20:52:47.847-0700", 
    "dateString": "2016-04-20T20:52:47.847-0700", 
    "sgv": 117, 
    "device": "xDrip-DexcomShare", 
    "xDrip_filtered": 129, 
    "unfiltered": 131000, 
    "xDrip_raw": 131, 
    "date": 1461210767847, 
    "rssi": 100, 
    "xDrip_calculated_current_slope": 3.3340001333600052e-06, 
    "xDrip_age_adjusted_raw_value": 131, 
    "xDrip_calculated_value": 117
  }, 
  {
    "filtered": 130000, 
    "direction": "Flat", 
    "noise": 1, 
    "raw": 115, 
    "type": "sgv", 
    "_id": "57184d8465110bbfc192c93c", 
    "sysTime": "2016-04-20T20:47:47.907-0700", 
    "dateString": "2016-04-20T20:47:47.907-0700", 
    "sgv": 116, 
    "device": "xDrip-DexcomShare", 
    "xDrip_filtered": 130, 
    "unfiltered": 129000, 
    "xDrip_raw": 129, 
    "date": 1461210467907, 
    "rssi": 100, 
    "xDrip_calculated_current_slope": 0, 
    "xDrip_age_adjusted_raw_value": 129, 
    "xDrip_calculated_value": 116
  }, 
  {
    "filtered": 132000, 
    "direction": "Flat", 
    "noise": 1, 
    "raw": 114, 
    "type": "sgv", 
    "_id": "57184c9865110bbfc192c93b", 
    "sysTime": "2016-04-20T20:42:47.441-0700", 
    "dateString": "2016-04-20T20:42:47.441-0700", 
    "sgv": 116, 
    "device": "xDrip-DexcomShare", 
    "xDrip_filtered": 132, 
    "unfiltered": 130000, 
    "xDrip_raw": 130, 
    "date": 1461210167441, 
    "rssi": 100, 
    "xDrip_calculated_current_slope": -3.3349007366795726e-06, 
    "xDrip_age_adjusted_raw_value": 130, 
    "xDrip_calculated_value": 116
  }, 
  {
    "filtered": 134000, 
    "direction": "Flat", 
    "noise": 1, 
    "raw": 112, 
    "type": "sgv", 
    "_id": "57184b3865110bbfc192c93a", 
    "sysTime": "2016-04-20T20:37:47.582-0700", 
    "dateString": "2016-04-20T20:37:47.582-0700", 
    "sgv": 117, 
    "device": "xDrip-DexcomShare", 
    "xDrip_filtered": 134, 
    "unfiltered": 130000, 
    "xDrip_raw": 130, 
    "date": 1461209867582, 
    "rssi": 100, 
    "xDrip_calculated_current_slope": -9.99653453469464e-06, 
    "xDrip_age_adjusted_raw_value": 130, 
    "xDrip_calculated_value": 117
  }
]